llm/__init__.py
llm/agent/__init__.py
llm/agent/ask_again.py
llm/agent/retry.py
llm/chat_model.py
llm/common.py
llm/embeddings.py
y_llm-0.3.1.dist-info/METADATA
y_llm-0.3.1.dist-info/WHEEL
y_llm-0.3.1.dist-info/RECORD
